[
  {
    "request": {
      "body": "",
      "headers": {
        "accept": "application/json;odata=minimalmetadata",
        "dataserviceversion": "3.0;NetFx",
        "x-ms-date": "Sat, 27 Mar 2021 12:34:44 GMT",
        "x-ms-version": "2019-07-07",
        "authorization": "***"
      },
      "method": "get",
      "options": {
        "ssl_options": {
          "versions": [
            "tlsv1.2"
          ]
        }
      },
      "request_body": "",
      "url": "https://account-name.table.core.windows.net/test?$filter=(PartitionKey%20eq%20'partition_key_1')&$top=1&NextPartitionKey=1!20!cGFydGl0aW9uX2tleV8x&NextRowKey=1!12!cm93X2tleV8z"
    },
    "response": {
      "binary": false,
      "body": "{\"odata.metadata\":\"https://account-name.table.core.windows.net/$metadata#test\",\"value\":[{\"odata.etag\":\"W/\\\"datetime'2021-03-27T10%3A02%3A57.4297348Z'\\\"\",\"PartitionKey\":\"partition_key_1\",\"RowKey\":\"row_key_3\",\"Timestamp\":\"2021-03-27T10:02:57.4297348Z\",\"Name\":\"Jasper\",\"Active\":true,\"Score\":20}]}",
      "headers": {
        "Cache-Control": "no-cache",
        "Transfer-Encoding": "chunked",
        "Content-Type": "application/json;odata=minimalmetadata;streaming=true;charset=utf-8",
        "Server": "Windows-Azure-Table/1.0 Microsoft-HTTPAPI/2.0",
        "x-ms-request-id": "92c31fc8-c002-0066-4e05-23830b000000",
        "x-ms-version": "2019-07-07",
        "X-Content-Type-Options": "nosniff",
        "x-ms-continuation-NextPartitionKey": "1!20!cGFydGl0aW9uX2tleV8x",
        "x-ms-continuation-NextRowKey": "1!12!cm93X2tleV80",
        "Date": "Sat, 27 Mar 2021 12:34:44 GMT"
      },
      "status_code": 200,
      "type": "ok"
    }
  }
]